{
  "fileId": "4",
  "extension": ".png",
  "totalChunks": 21,
  "startTime": 1768829853,
  "chunks": {
    "0": "completed",
    "1": "completed",
    "2": "completed",
    "3": "completed",
    "4": "completed",
    "5": "completed",
    "6": "completed",
    "7": "completed",
    "8": "completed",
    "9": "completed",
    "10": "completed",
    "11": "completed",
    "12": "pending",
    "13": "pending",
    "14": "pending",
    "15": "pending",
    "16": "pending",
    "17": "pending",
    "18": "pending",
    "19": "pending",
    "20": "pending"
  }
}